pygame_snake/__init__.py
pygame_snake/main.py
python_snake_game/__init__.py
python_snake_game/main.py
snake_game_python/__init__.py
snake_game_python/main.py
snake_python/__init__.py
snake_python/main.py
snake_game_python-1.1.0.dist-info/LICENSE
snake_game_python-1.1.0.dist-info/METADATA
snake_game_python-1.1.0.dist-info/WHEEL
snake_game_python-1.1.0.dist-info/entry_points.txt
snake_game_python-1.1.0.dist-info/top_level.txt
snake_game_python-1.1.0.dist-info/RECORD
