Metadata-Version: 2.1
Name: snake-game-python
Version: 1.1.0
Summary: A simple snake clone writen in python
Home-page: https://github.com/CommanderRedYT/snake-python
Author: CommanderRedYT
License: GPLv3
Platform: UNKNOWN
Requires-Python: >=3.6
License-File: LICENSE
Requires-Dist: pygame (>=2.1.2)
Requires-Dist: pygame-menu (>=4.2.2)
